{"updatedAt":"2026-07-05T10:52:33.177Z","identite":{"civ":"M.","prenom":"Charles","nom":"Sitzenstuhl","nomComplet":"Charles Sitzenstuhl","female":false,"dateNaissance":"1988-12-03","villeNaissance":"Sélestat","profession":"Cadre de la fonction publique"},"mandat":{"dateDebut":"2024-07-07","dateFin":null,"legislature":"17","causeMandat":"élections générales","premiereElection":true,"placeHemicycle":"364","circonscription":{"numero":"5","libelle":"5e circonscription","departement":"Bas-Rhin","numDepartement":"67","region":"Grand Est"},"groupe":{"id":"epr","short":"EPR","name":"Ensemble pour la République","color":"#2563EB"},"commissions":[{"nom":"Commission des finances, de l'économie générale et du contrôle budgétaire","court":"Finances, de l'économie générale et du contrôle budgétaire","qualite":"Membre"}],"suppleant":null},"stats":{"taux_participation":0.6082,"taux_loyaute":0.8752,"moyenne_groupe_loyaute":0.9541,"moyenne_groupe_participation":0.2162,"nb_scrutins_mandat":7978,"nb_votes_exprimes":4852,"pour":1651,"contre":3164,"abstention":37,"nb_non_votant":0,"nb_delegations":124,"nb_votes_rebelles":60,"nb_amendements":674,"nb_amendements_adoptes":36,"nb_amendements_sort_connu":425,"nb_amendements_cosignes":1152,"taux_adoption_amendements":0.0847,"nb_questions_ecrites":25,"nb_questions_orales":3,"nb_questions_gouvernement":1,"nb_questions_avec_reponse":17,"nb_rapports":7},"loyaute_applicable":true,"votes_rebelles":[{"n":"7894","d":"2026-06-30","t":"l'ensemble de la proposition de loi relative au droit à l'aide à mourir (nouvelle lecture).","p":"c","g":"p","sol":true},{"n":"7801","d":"2026-06-27","t":"l'amendement n° 789 de Mme Blin et l'amendement identique suivant de suppression de l'article 16 de la proposition de loi relative au droit à l'aide à mourir (nouvelle lecture).","p":"p","g":"c"},{"n":"7800","d":"2026-06-27","t":"l'article 15 de la proposition de loi relative au droit à l'aide à mourir (nouvelle lecture).","p":"c","g":"p"},{"n":"7798","d":"2026-06-27","t":"l'amendement n° 1585 de M. Potier à l'article 15 de la proposition de loi relative au droit à l'aide à mourir (nouvelle lecture).","p":"p","g":"c"},{"n":"7795","d":"2026-06-27","t":"l'amendement n° 508 de Mme Gruet et les amendements identiques suivants à l'article 14 de la proposition de loi relative au droit à l'aide à mourir (nouvelle lecture).","p":"p","g":"c"},{"n":"7790","d":"2026-06-27","t":"l'amendement n° 713 de Mme Colin-Oesterlé et les amendements identique suivants à l'article 14 de la proposition de loi relative au droit à l'aide à mourir (nouvelle lecture).","p":"p","g":"c"},{"n":"7789","d":"2026-06-27","t":"l'article 13 de la proposition de loi relative au droit à l'aide à mourir (nouvelle lecture).","p":"c","g":"p"},{"n":"7788","d":"2026-06-27","t":"l'article 12 de la proposition de loi relative au droit à l'aide à mourir (nouvelle lecture).","p":"c","g":"p"},{"n":"7784","d":"2026-06-27","t":"l'amendement n° 75 de M. Hetzel à l'article 12 de la proposition de loi relative au droit à l'aide à mourir (nouvelle lecture).","p":"p","g":"c"},{"n":"7690","d":"2026-06-26","t":"l'amendement n° 733 de Mme Colin-Oesterlé et les amendements identiques suivants à l'article 6 de la proposition de loi relative au droit à l'aide à mourir (nouvelle lecture).","p":"p","g":"c"},{"n":"7689","d":"2026-06-26","t":"l'amendement n° 443  de Mme Gruet à l'article 6 de la proposition de loi relative au droit à l'aide à mourir (nouvelle lecture).","p":"p","g":"c"},{"n":"7688","d":"2026-06-26","t":"l'amendement n° 23 de M. Frappé et les amendements identiques suivants à l'article 6 de la proposition de loi relative au droit à l'aide à mourir (nouvelle lecture).","p":"p","g":"c"},{"n":"7687","d":"2026-06-26","t":"l'amendement n° 60 de M. Hetzel à l'article 6 de la proposition de loi relative au droit à l'aide à mourir (nouvelle lecture).","p":"p","g":"c"},{"n":"7686","d":"2026-06-26","t":"l'amendement n° 446 de Mme Gruet à l'article 6 de la proposition de loi relative au droit à l'aide à mourir (nouvelle lecture).","p":"p","g":"c"},{"n":"7685","d":"2026-06-26","t":"l'amendement n° 7 de M. Bazin à l'article 6 de la proposition de loi relative au droit à l'aide à mourir (nouvelle lecture).","p":"p","g":"c"},{"n":"7684","d":"2026-06-26","t":"l'amendement n° 583 de M. Hetzel à l'article 6 de la proposition de loi relative au droit à l'aide à mourir (nouvelle lecture).","p":"p","g":"c"},{"n":"7683","d":"2026-06-26","t":"l'amendement n° 544 de Mme Corneloup à l'article 6 de la proposition de loi relative au droit à l'aide à mourir (nouvelle lecture).","p":"p","g":"c"},{"n":"7682","d":"2026-06-26","t":"l'amendement n° 1334 de M. Ray à l'article 6 de la proposition de loi relative au droit à l'aide à mourir (nouvelle lecture).","p":"p","g":"c"},{"n":"7681","d":"2026-06-26","t":"l'amendement n° 914 de M. Juvin à l'article 6 de la proposition de loi relative au droit à l'aide à mourir (nouvelle lecture).","p":"p","g":"c"},{"n":"7680","d":"2026-06-26","t":"l'amendement n° 1251 de Mme Gruet à l'article 6 de la proposition de loi relative au droit à l'aide à mourir (nouvelle lecture).","p":"p","g":"c"},{"n":"7679","d":"2026-06-26","t":"l'amendement n° 913 de M. Juvin à l'article 6 de la proposition de loi relative au droit à l'aide à mourir (nouvelle lecture).","p":"p","g":"c"},{"n":"7678","d":"2026-06-26","t":"l'amendement n° 321 de Mme Corneloup à l'article 6 de la proposition de loi relative au droit à l'aide à mourir (nouvelle lecture).","p":"p","g":"c"},{"n":"7677","d":"2026-06-26","t":"l'amendement n° 207 de M. Hetzel et l'amendement identique suivant à l'article 6 de la proposition de loi relative au droit à l'aide à mourir (nouvelle lecture).","p":"p","g":"c"},{"n":"7675","d":"2026-06-26","t":"l'amendement n° 812 de Mme Vidal à l'article 6 de la proposition de loi relative au droit à l'aide à mourir (nouvelle lecture).","p":"p","g":"c"},{"n":"7674","d":"2026-06-26","t":"l'amendement n° 911 de M. Juvin à l'article 6 de la proposition de loi relative au droit à l'aide à mourir (nouvelle lecture).","p":"p","g":"c"},{"n":"7673","d":"2026-06-26","t":"l'amendement n° 910 de M. Juvin à l'article 6 de la proposition de loi relative au droit à l'aide à mourir (nouvelle lecture).","p":"p","g":"c"},{"n":"7672","d":"2026-06-26","t":"l'amendement n° 584 de M. Hetzel à l'article 6 de la proposition de loi relative au droit à l'aide à mourir (nouvelle lecture).","p":"p","g":"c"},{"n":"7671","d":"2026-06-26","t":"l'amendement n° 1391 de M. Neuder à l'article 6 de la proposition de loi relative au droit à l'aide à mourir (nouvelle lecture).","p":"p","g":"c"},{"n":"7670","d":"2026-06-26","t":"l'amendement n° 909 de M. Juvin à l'article 6 de la proposition de loi relative au droit à l'aide à mourir (nouvelle lecture).","p":"p","g":"c"},{"n":"7667","d":"2026-06-26","t":"l'amendement n° 582 de M. Hetzel à l'article 6 de la proposition de loi relative au droit à l'aide à mourir (nouvelle lecture).","p":"p","g":"c"},{"n":"7666","d":"2026-06-26","t":"l'amendement n° 1216 de Mme Joncour et l'amendement identique suivant à l'article 6 de la proposition de loi relative au droit à l'aide à mourir (nouvelle lecture).","p":"p","g":"c"},{"n":"7665","d":"2026-06-26","t":"l'amendement n° 59 de M. Hetzel à l'article 6 de la proposition de loi relative au droit à l'aide à mourir (nouvelle lecture).","p":"p","g":"c"},{"n":"7664","d":"2026-06-26","t":"l'amendement n° 84 de M. Hetzel et les amendements identiques suivants à l'article 6 de la proposition de loi relative au droit à l'aide à mourir (nouvelle lecture).","p":"p","g":"c"},{"n":"7663","d":"2026-06-26","t":"l'amendement n° 906 de M. Juvin à l'article 6 de la proposition de loi relative au droit à l'aide à mourir (nouvelle lecture).","p":"p","g":"c"},{"n":"7662","d":"2026-06-26","t":"l'amendement n° 251 de M. Hetzel à l'article 6 de la proposition de loi relative au droit à l'aide à mourir (nouvelle lecture).","p":"p","g":"c"},{"n":"7661","d":"2026-06-26","t":"l'amendement n° 438 de Mme Gruet à l'article 6 de la proposition de loi relative au droit à l'aide à mourir (nouvelle lecture).","p":"p","g":"c"},{"n":"7660","d":"2026-06-26","t":"l'amendement n° 905 de M. Juvin à l'article 6 de la proposition de loi relative au droit à l'aide à mourir (nouvelle lecture).","p":"p","g":"c"},{"n":"7659","d":"2026-06-26","t":"l'amendement n° 58 de M. Hetzel à l'article 6 de la proposition de loi relative au droit à l'aide à mourir (nouvelle lecture).","p":"p","g":"c"},{"n":"7650","d":"2026-06-26","t":"l'amendement n° 8 de M. Bazin  et les amendements identiques suivants à l'article 6 de la proposition de loi relative au droit à l'aide à mourir (nouvelle lecture).","p":"p","g":"c"},{"n":"7649","d":"2026-06-26","t":"l'amendement n° 904 de M. Juvin à l'article 6 de la proposition de loi relative au droit à l'aide à mourir (nouvelle lecture).","p":"p","g":"c"},{"n":"7648","d":"2026-06-26","t":"l'amendement n° 433 de Mme Gruet à l'article 6 de la proposition de loi relative au droit à l'aide à mourir (nouvelle lecture).","p":"p","g":"c"},{"n":"7647","d":"2026-06-26","t":"l'amendement n° 431 de Mme Gruet à l'article 6 de la proposition de loi relative au droit à l'aide à mourir (nouvelle lecture).","p":"p","g":"c"},{"n":"7646","d":"2026-06-26","t":"l'article 5 de la proposition de loi relative au droit à l'aide à mourir (nouvelle lecture).","p":"c","g":"p"},{"n":"7645","d":"2026-06-26","t":"l'amendement n° 430 de Mme Gruet à l'article 5 de la proposition de loi relative au droit à l'aide à mourir (nouvelle lecture).","p":"p","g":"c"},{"n":"7644","d":"2026-06-26","t":"l'amendement n° 429 de Mme Gruet à l'article 5 de la proposition de loi relative au droit à l'aide à mourir (nouvelle lecture).","p":"p","g":"c"},{"n":"7641","d":"2026-06-26","t":"l'amendement n° 1333 de M. Ray à l'article 5 de la proposition de loi relative au droit à l'aide à mourir (nouvelle lecture).","p":"p","g":"c"},{"n":"7640","d":"2026-06-26","t":"l'amendement n° 901 de M. Juvin à l'article 5 de la proposition de loi relative au droit à l'aide à mourir (nouvelle lecture).","p":"p","g":"c"},{"n":"7639","d":"2026-06-26","t":"l'amendement n° 428 de Mme Gruet à l'article 5 de la proposition de loi relative au droit à l'aide à mourir (nouvelle lecture).","p":"p","g":"c"},{"n":"7638","d":"2026-06-26","t":"l'amendement n° 427 de Mme Gruet à l'article 5 de la proposition de loi relative au droit à l'aide à mourir (nouvelle lecture).","p":"p","g":"c"},{"n":"7637","d":"2026-06-26","t":"l'amendement n° 902 de M. Juvin à l'article 5 de la proposition de loi relative au droit à l'aide à mourir (nouvelle lecture).","p":"p","g":"c"},{"n":"7636","d":"2026-06-26","t":"l'amendement n° 426 de Mme Gruet à l'article 5 de la proposition de loi relative au droit à l'aide à mourir (nouvelle lecture).","p":"p","g":"c"},{"n":"7635","d":"2026-06-26","t":"l'amendement n° 425 de Mme Gruet à l'article 5 de la proposition de loi relative au droit à l'aide à mourir (nouvelle lecture).","p":"p","g":"c"},{"n":"7554","d":"2026-06-24","t":"l'amendement n° 888 de M. Juvin à l’article 4 de la proposition de loi relative au droit à l’aide à mourir (nouvelle lecture).","p":"p","g":"c"},{"n":"7553","d":"2026-06-24","t":"l'amendement n° 411 de Mme Gruet à l’article 4 de la proposition de loi relative au droit à l’aide à mourir (nouvelle lecture).","p":"p","g":"c"},{"n":"7548","d":"2026-06-24","t":"l'amendement n° 751 de Mme Blin et l'amendement identique suivant à l’article 4 de la proposition de loi relative au droit à l’aide à mourir (nouvelle lecture).","p":"p","g":"c"},{"n":"7547","d":"2026-06-24","t":"l'amendement n° 1058 de M. Pilato à l’article 4 de la proposition de loi relative au droit à l’aide à mourir (nouvelle lecture).","p":"c","g":"p"},{"n":"7546","d":"2026-06-24","t":"l'amendement n° 1057 de M. Pilato à l’article 4 de la proposition de loi relative au droit à l’aide à mourir (nouvelle lecture).","p":"c","g":"p"},{"n":"7544","d":"2026-06-24","t":"l'amendement n° 229 de Mme Lorho et l'amendement identique suivant à l’article 4 de la proposition de loi relative au droit à l’aide à mourir (nouvelle lecture).","p":"p","g":"c"},{"n":"7542","d":"2026-06-24","t":"l'amendement n° 356 de Mme Corneloup à l’article 4 de la proposition de loi relative au droit à l’aide à mourir (nouvelle lecture).","p":"p","g":"c"},{"n":"7539","d":"2026-06-24","t":"l'amendement n° 37 de M. Hetzel et les amendements identiques suivants à l’article 4 de la proposition de loi relative au droit à l’aide à mourir (nouvelle lecture).","p":"p","g":"c"}],"derniers_votes":[{"n":"7978","d":"2026-07-02","t":"l'article 2 du projet de loi organique relatif au renforcement des juridctions criminelles (première lecture).","p":"abs"},{"n":"7977","d":"2026-07-02","t":"l'amendement n° 22 de M. Coulomme de suppression de l'article 2 du projet de loi organique relatif au renforcement des juridctions criminelles (première lecture).","p":"abs"},{"n":"7976","d":"2026-07-02","t":"l'amendement n° 8 de Mme Thiébault-Martinez à l'article 1er bis du projet de loi organique relatif au renforcement des juridctions criminelles (première lecture).","p":"abs"},{"n":"7975","d":"2026-07-02","t":"l'article premier du projet de loi organique relatif au renforcement des juridctions criminelles (première lecture).","p":"abs"},{"n":"7974","d":"2026-07-02","t":"l'amendement n° 164 de M. Coulomme après l'article 12 du projet de loi sur la justice criminelle et le respect des victimes (première lecture).","p":"abs"},{"n":"7973","d":"2026-07-02","t":"l'amendement n° 96 de Mme Capdevielle après l'article 12 du projet de loi sur la justice criminelle et le respect des victimes (première lecture).","p":"abs"},{"n":"7972","d":"2026-07-02","t":"l'amendement n° 95 de Mme Capdevielle après l'article 12 du projet de loi sur la justice criminelle et le respect des victimes (première lecture).","p":"abs"},{"n":"7971","d":"2026-07-02","t":"l'amendement n° 208 de M. Coulomme après l'article 12 du projet de loi sur la justice criminelle et le respect des victimes (première lecture).","p":"abs"},{"n":"7970","d":"2026-07-02","t":"l'article 12 du projet de loi sur la justice criminelle et le respect des victimes (première lecture).","p":"abs"},{"n":"7969","d":"2026-07-02","t":"l'amendement n° 203 de M. Coulomme de suppression de l'article 12 du projet de loi sur la justice criminelle et le respect des victimes (première lecture).","p":"abs"},{"n":"7968","d":"2026-07-02","t":"l'article 11 du projet de loi sur la justice criminelle et le respect des victimes (première lecture).","p":"abs"},{"n":"7967","d":"2026-07-02","t":"l'amendement n° 202 de Mme Cathala de suppression de l'article 11 du projet de loi sur la justice criminelle et le respect des victimes (première lecture).","p":"abs"},{"n":"7966","d":"2026-07-02","t":"l'amendement n° 6 de M. Houlié et les amendements identiques suivants de suppression de l'article 10 du projet de loi sur la justice criminelle et le respect des victimes (première lecture).","p":"abs"},{"n":"7965","d":"2026-07-02","t":"l'amendement n° 199 de M. Coulomme après l'article 9 du projet de loi sur la justice criminelle et le respect des victimes (première lecture).","p":"abs"},{"n":"7964","d":"2026-07-02","t":"l'amendement n° 198 de M. Coulomme après l'article 9 du projet de loi sur la justice criminelle et le respect des victimes (première lecture).","p":"abs"},{"n":"7963","d":"2026-07-02","t":"l'amendement n° 332 de M. Coulomme après l'article 9 du projet de loi sur la justice criminelle et le respect des victimes (première lecture).","p":"abs"},{"n":"7962","d":"2026-07-02","t":"l'article 9 du projet de loi sur la justice criminelle et le respect des victimes (première lecture).","p":"abs"},{"n":"7961","d":"2026-07-02","t":"l'amendement n° 91 de Mme Capdevielle et l'amendement identique suivant à l'article 9 du projet de loi sur la justice criminelle et le respect des victimes (première lecture).","p":"abs"},{"n":"7960","d":"2026-07-02","t":"l'amendement n° 90 de Mme Capdevielle à l'article 9 du projet de loi sur la justice criminelle et le respect des victimes (première lecture).","p":"abs"},{"n":"7959","d":"2026-07-02","t":"l'amendement n° 260 de M. Duplessy à l'article 9 du projet de loi sur la justice criminelle et le respect des victimes (première lecture).","p":"abs"},{"n":"7958","d":"2026-07-02","t":"l'amendement n° 24 de Mme K/Bidi et les amendements identiques suivants de suppression de l'article 9 du projet de loi sur la justice criminelle et le respect des victimes (première lecture).","p":"abs"},{"n":"7957","d":"2026-07-02","t":"l'amendement n° 193 de M. Coulomme et l'amendement identique suivant de suppression de l'article 8 du projet de loi sur la justice criminelle et le respect des victimes (première lecture).","p":"abs"},{"n":"7956","d":"2026-07-02","t":"l'amendement n° 331 de M. Coulomme après l'article 7 du projet de loi sur la justice criminelle et le respect des victimes (première lecture).","p":"abs"},{"n":"7955","d":"2026-07-02","t":"l'article 7 du projet de loi sur la justice criminelle et le respect des victimes (première lecture).","p":"abs"},{"n":"7954","d":"2026-07-02","t":"l'amendement n° 86 de Mme Capdevielle à l'article 7 du projet de loi sur la justice criminelle et le respect des victimes (première lecture).","p":"abs"},{"n":"7953","d":"2026-07-02","t":"l'amendement n° 85 de Mme Capdevielle à l'article 7 du projet de loi sur la justice criminelle et le respect des victimes (première lecture).","p":"abs"},{"n":"7952","d":"2026-07-02","t":"l'amendement n° 329 de Mme Cathala à l'article 7 du projet de loi sur la justice criminelle et le respect des victimes (première lecture).","p":"abs"},{"n":"7951","d":"2026-07-02","t":"l'amendement n° 15 de Mme K/Bidi et les amendements identiques suivants de suppression de l'article 7 du projet de loi sur la justice criminelle et le respect des victimes (première lecture).","p":"abs"},{"n":"7950","d":"2026-07-02","t":"l'aticle 6 du projet de loi sur la justice criminelle et le respect des victimes (première lecture).","p":"abs"},{"n":"7949","d":"2026-07-02","t":"l'amendement n° 83 de Mme Thiébault-Martinez à l'aticle 6 du projet de loi sur la justice criminelle et le respect des victimes (première lecture).","p":"abs"},{"n":"7948","d":"2026-07-02","t":"l'amendement n° 253 de M. Duplessy à l'aticle 6 du projet de loi sur la justice criminelle et le respect des victimes (première lecture).","p":"abs"},{"n":"7947","d":"2026-07-02","t":"l'amendement n° 250 de M. Duplessy à l'aticle 6 du projet de loi sur la justice criminelle et le respect des victimes (première lecture).","p":"abs"},{"n":"7946","d":"2026-07-02","t":"l'amendement n° 80 de Mme Thiébault-Martinez et l'amendement identique suivant de suppression de l'article 6 du projet de loi sur la justice criminelle et le respect des victimes (première lecture).","p":"abs"},{"n":"7945","d":"2026-07-02","t":"l'article 5 du projet de loi sur la justice criminelle et le respect des victimes (première lecture).","p":"abs"},{"n":"7944","d":"2026-07-02","t":"l'amendement n° 190 de M. Coulomme à l'article 5 du projet de loi sur la justice criminelle et le respect des victimes (première lecture).","p":"abs"},{"n":"7943","d":"2026-07-02","t":"l'amendement n° 79 de Mme Thiébault-Martinez et l'amendement identique suivant de suppression de l'article 5 du projet de loi sur la justice criminelle et le respect des victimes (première lecture).","p":"abs"},{"n":"7942","d":"2026-07-02","t":"l'article 4 du projet de loi sur la justice criminelle et le respect des victimes (première lecture).","p":"abs"},{"n":"7941","d":"2026-07-02","t":"l'amendement n° 189 de Mme Cathala après l'article 3 du projet de loi sur la justice criminelle et le respect des victimes (première lecture).","p":"abs"},{"n":"7940","d":"2026-07-02","t":"l'article 3 du projet de loi sur la justice criminelle et le respect des victimes (première lecture).","p":"abs"},{"n":"7939","d":"2026-07-02","t":"l'amendement n° 78 de Mme Capdevielle à l'article 3 du projet de loi sur la justice criminelle et le respect des victimes (première lecture).","p":"abs"},{"n":"7938","d":"2026-07-02","t":"l'amendement n° 248 (rect.) de M. Duplessy à l'article 3 du projet de loi sur la justice criminelle et le respect des victimes (première lecture).","p":"abs"},{"n":"7937","d":"2026-07-02","t":"l'amendement n° 77 de Mme Capdevielle et l'amendement identique suivant à l'article 3 du projet de loi sur la justice criminelle et le respect des victimes (première lecture).","p":"abs"},{"n":"7936","d":"2026-07-02","t":"l'amendement n° 76 de Mme Capdevielle et l'amendement identique suivant à l'article 3 du projet de loi sur la justice criminelle et le respect des victimes (première lecture).","p":"abs"},{"n":"7935","d":"2026-07-02","t":"l'amendement n° 247 de M. Duplessy à l'article 3 du projet de loi sur la justice criminelle et le respect des victimes (première lecture).","p":"abs"},{"n":"7934","d":"2026-07-02","t":"l'amendement n° 310 de M. Molac à l'article 3 du projet de loi sur la justice criminelle et le respect des victimes (première lecture).","p":"abs"},{"n":"7933","d":"2026-07-02","t":"l'amendement n° 176 de Mme Cathala à l'article 3 du projet de loi sur la justice criminelle et le respect des victimes (première lecture).","p":"abs"},{"n":"7932","d":"2026-07-01","t":"l'amendement n° 285 de Mme Bergantz et l'amendement identique suivant à l'article 3 du projet de loi sur la justice criminelle et le respect des victimes (première lecture).","p":"abs"},{"n":"7931","d":"2026-07-01","t":"l'amendement n° 99 de M. Gery à l'article 3 du projet de loi sur la justice criminelle et le respect des victimes (première lecture).","p":"abs"},{"n":"7930","d":"2026-07-01","t":"l'amendement n° 181 de M. Coulomme à l'article 3 du projet de loi sur la justice criminelle et le respect des victimes (première lecture).","p":"abs"},{"n":"7929","d":"2026-07-01","t":"l'amendement n° 74 de Mme Capdevielle et l'amendement identique suivant à l'article 3 du projet de loi sur la justice criminelle et le respect des victimes (première lecture).","p":"abs"}],"nb_total_derniers_votes":7978,"amendements":[{"num":"6","d":"2026-06-22","s":"En cours","t":"Renforcer la souveraineté alimentaire par le développement des circuits de proximité dans la restauration collective publique","div":"ART. PREMIER","nc":0},{"num":"957","d":"2026-06-17","s":"Rejeté","t":"Droit à l'aide à mourir","div":"ART. 3","nc":0},{"num":"1009","d":"2026-06-17","s":"En cours","t":"Droit à l'aide à mourir","div":"ART. 7","nc":0},{"num":"963","d":"2026-06-17","s":"Rejeté","t":"Droit à l'aide à mourir","div":"ART. 4","nc":0},{"num":"1016","d":"2026-06-17","s":"Non soutenu","t":"Droit à l'aide à mourir","div":"ART. 10","nc":0},{"num":"984","d":"2026-06-17","s":"En cours","t":"Droit à l'aide à mourir","div":"ART. 6","nc":0},{"num":"967","d":"2026-06-17","s":"Rejeté","t":"Droit à l'aide à mourir","div":"ART. 4","nc":0},{"num":"1001","d":"2026-06-17","s":"En cours","t":"Droit à l'aide à mourir","div":"ART. 6","nc":0},{"num":"1024","d":"2026-06-17","s":"En cours","t":"Droit à l'aide à mourir","div":"ART. 16","nc":0},{"num":"969","d":"2026-06-17","s":"Rejeté","t":"Droit à l'aide à mourir","div":"ART. 4","nc":0},{"num":"976","d":"2026-06-17","s":"Non soutenu","t":"Droit à l'aide à mourir","div":"ART. 5","nc":0},{"num":"952","d":"2026-06-17","s":"Rejeté","t":"Droit à l'aide à mourir","div":"ART. 2","nc":0},{"num":"982","d":"2026-06-17","s":"Non soutenu","t":"Droit à l'aide à mourir","div":"ART. 5","nc":0},{"num":"1010","d":"2026-06-17","s":"En cours","t":"Droit à l'aide à mourir","div":"ART. 7","nc":0},{"num":"1011","d":"2026-06-17","s":"En cours","t":"Droit à l'aide à mourir","div":"ART. 8","nc":0},{"num":"998","d":"2026-06-17","s":"En cours","t":"Droit à l'aide à mourir","div":"ART. 6","nc":0},{"num":"975","d":"2026-06-17","s":"Non soutenu","t":"Droit à l'aide à mourir","div":"ART. 5","nc":0},{"num":"951","d":"2026-06-17","s":"Rejeté","t":"Droit à l'aide à mourir","div":"ART. 2","nc":0},{"num":"1026","d":"2026-06-17","s":"En cours","t":"Droit à l'aide à mourir","div":"ART. 6","nc":0},{"num":"1019","d":"2026-06-17","s":"Rejeté","t":"Droit à l'aide à mourir","div":"ART. 14","nc":0},{"num":"960","d":"2026-06-17","s":"Rejeté","t":"Droit à l'aide à mourir","div":"ART. 4","nc":0},{"num":"974","d":"2026-06-17","s":"Non soutenu","t":"Droit à l'aide à mourir","div":"ART. 4","nc":0},{"num":"966","d":"2026-06-17","s":"Rejeté","t":"Droit à l'aide à mourir","div":"ART. 4","nc":0},{"num":"971","d":"2026-06-17","s":"Rejeté","t":"Droit à l'aide à mourir","div":"ART. 4","nc":0},{"num":"949","d":"2026-06-17","s":"En cours","t":"Droit à l'aide à mourir","div":"ART. 2","nc":0},{"num":"990","d":"2026-06-17","s":"En cours","t":"Droit à l'aide à mourir","div":"ART. 6","nc":0},{"num":"1013","d":"2026-06-17","s":"Non soutenu","t":"Droit à l'aide à mourir","div":"ART. 9","nc":0},{"num":"989","d":"2026-06-17","s":"En cours","t":"Droit à l'aide à mourir","div":"ART. 6","nc":0},{"num":"972","d":"2026-06-17","s":"Rejeté","t":"Droit à l'aide à mourir","div":"ART. 4","nc":0},{"num":"970","d":"2026-06-17","s":"Rejeté","t":"Droit à l'aide à mourir","div":"ART. 4","nc":0},{"num":"964","d":"2026-06-17","s":"Rejeté","t":"Droit à l'aide à mourir","div":"ART. 4","nc":0},{"num":"1021","d":"2026-06-17","s":"Rejeté","t":"Droit à l'aide à mourir","div":"ART. 14","nc":0},{"num":"979","d":"2026-06-17","s":"Non soutenu","t":"Droit à l'aide à mourir","div":"ART. 5","nc":0},{"num":"1028","d":"2026-06-17","s":"Non soutenu","t":"Droit à l'aide à mourir","div":"ART. 9","nc":0},{"num":"965","d":"2026-06-17","s":"Rejeté","t":"Droit à l'aide à mourir","div":"ART. 4","nc":0},{"num":"1023","d":"2026-06-17","s":"En cours","t":"Droit à l'aide à mourir","div":"ART. 15","nc":0},{"num":"1007","d":"2026-06-17","s":"En cours","t":"Droit à l'aide à mourir","div":"ART. 7","nc":0},{"num":"999","d":"2026-06-17","s":"En cours","t":"Droit à l'aide à mourir","div":"ART. 6","nc":0},{"num":"1006","d":"2026-06-17","s":"En cours","t":"Droit à l'aide à mourir","div":"ART. 7","nc":0},{"num":"1025","d":"2026-06-17","s":"Non soutenu","t":"Droit à l'aide à mourir","div":"ART. 5","nc":0},{"num":"1003","d":"2026-06-17","s":"En cours","t":"Droit à l'aide à mourir","div":"ART. 6","nc":0},{"num":"995","d":"2026-06-17","s":"En cours","t":"Droit à l'aide à mourir","div":"ART. 6","nc":0},{"num":"994","d":"2026-06-17","s":"Rejeté","t":"Droit à l'aide à mourir","div":"ART. 6","nc":0},{"num":"1000","d":"2026-06-17","s":"En cours","t":"Droit à l'aide à mourir","div":"ART. 6","nc":0},{"num":"1027","d":"2026-06-17","s":"En cours","t":"Droit à l'aide à mourir","div":"ART. 7","nc":0},{"num":"968","d":"2026-06-17","s":"En cours","t":"Droit à l'aide à mourir","div":"ART. 4","nc":0},{"num":"872","d":"2026-06-17","s":"Rejeté","t":"Droit à l'aide à mourir","div":"ART. 2","nc":0},{"num":"981","d":"2026-06-17","s":"Non soutenu","t":"Droit à l'aide à mourir","div":"ART. 5","nc":0},{"num":"954","d":"2026-06-17","s":"Rejeté","t":"Droit à l'aide à mourir","div":"ART. 2","nc":0},{"num":"991","d":"2026-06-17","s":"Rejeté","t":"Droit à l'aide à mourir","div":"ART. 6","nc":0},{"num":"988","d":"2026-06-17","s":"En cours","t":"Droit à l'aide à mourir","div":"ART. 6","nc":0},{"num":"1014","d":"2026-06-17","s":"Non soutenu","t":"Droit à l'aide à mourir","div":"ART. 9","nc":0},{"num":"1015","d":"2026-06-17","s":"Non soutenu","t":"Droit à l'aide à mourir","div":"ART. 9","nc":0},{"num":"962","d":"2026-06-17","s":"Rejeté","t":"Droit à l'aide à mourir","div":"ART. 4","nc":0},{"num":"1022","d":"2026-06-17","s":"Rejeté","t":"Droit à l'aide à mourir","div":"ART. 15","nc":0},{"num":"1018","d":"2026-06-17","s":"Rejeté","t":"Droit à l'aide à mourir","div":"ART. 12","nc":0},{"num":"1017","d":"2026-06-17","s":"Non soutenu","t":"Droit à l'aide à mourir","div":"ART. 11","nc":0},{"num":"987","d":"2026-06-17","s":"Non soutenu","t":"Droit à l'aide à mourir","div":"ART. 6","nc":0},{"num":"986","d":"2026-06-17","s":"Rejeté","t":"Droit à l'aide à mourir","div":"ART. 6","nc":0},{"num":"1004","d":"2026-06-17","s":"En cours","t":"Droit à l'aide à mourir","div":"ART. 6","nc":0},{"num":"997","d":"2026-06-17","s":"En cours","t":"Droit à l'aide à mourir","div":"ART. 6","nc":0},{"num":"961","d":"2026-06-17","s":"Rejeté","t":"Droit à l'aide à mourir","div":"ART. 4","nc":0},{"num":"873","d":"2026-06-17","s":"Rejeté","t":"Droit à l'aide à mourir","div":"ART. 2","nc":0},{"num":"1002","d":"2026-06-17","s":"En cours","t":"Droit à l'aide à mourir","div":"ART. 6","nc":0},{"num":"958","d":"2026-06-17","s":"Rejeté","t":"Droit à l'aide à mourir","div":"ART. 3","nc":0},{"num":"978","d":"2026-06-17","s":"Non soutenu","t":"Droit à l'aide à mourir","div":"ART. 5","nc":0},{"num":"1020","d":"2026-06-17","s":"Rejeté","t":"Droit à l'aide à mourir","div":"ART. 14","nc":0},{"num":"992","d":"2026-06-17","s":"Rejeté","t":"Droit à l'aide à mourir","div":"ART. 6","nc":0},{"num":"950","d":"2026-06-17","s":"Tombé","t":"Droit à l'aide à mourir","div":"ART. 2","nc":0},{"num":"953","d":"2026-06-17","s":"Rejeté","t":"Droit à l'aide à mourir","div":"ART. 2","nc":0},{"num":"955","d":"2026-06-17","s":"Tombé","t":"Droit à l'aide à mourir","div":"ART. 2","nc":0},{"num":"985","d":"2026-06-17","s":"Non soutenu","t":"Droit à l'aide à mourir","div":"ART. 6","nc":0},{"num":"1012","d":"2026-06-17","s":"Non soutenu","t":"Droit à l'aide à mourir","div":"ART. 9","nc":0},{"num":"1005","d":"2026-06-17","s":"En cours","t":"Droit à l'aide à mourir","div":"ART. 6","nc":0},{"num":"956","d":"2026-06-17","s":"Rejeté","t":"Droit à l'aide à mourir","div":"ART. 3","nc":0},{"num":"977","d":"2026-06-17","s":"Non soutenu","t":"Droit à l'aide à mourir","div":"ART. 5","nc":0},{"num":"973","d":"2026-06-17","s":"Rejeté","t":"Droit à l'aide à mourir","div":"ART. 4","nc":0},{"num":"993","d":"2026-06-17","s":"Rejeté","t":"Droit à l'aide à mourir","div":"ART. 6","nc":0},{"num":"1008","d":"2026-06-17","s":"En cours","t":"Droit à l'aide à mourir","div":"ART. 7","nc":0},{"num":"980","d":"2026-06-17","s":"Non soutenu","t":"Droit à l'aide à mourir","div":"ART. 5","nc":0},{"num":"996","d":"2026-06-17","s":"En cours","t":"Droit à l'aide à mourir","div":"ART. 6","nc":0},{"num":"624","d":"2026-06-16","s":"Rejeté","t":"Droit à l'aide à mourir","div":"ART. 2","nc":0},{"num":"618","d":"2026-06-16","s":"Rejeté","t":"Droit à l'aide à mourir","div":"ART. 13","nc":0},{"num":"606","d":"2026-06-16","s":"Rejeté","t":"Droit à l'aide à mourir","div":"ART. PREMIER","nc":0},{"num":"617","d":"2026-06-16","s":"Non soutenu","t":"Droit à l'aide à mourir","div":"ART. 12","nc":0},{"num":"613","d":"2026-06-16","s":"Non soutenu","t":"Droit à l'aide à mourir","div":"ART. 9","nc":0},{"num":"611","d":"2026-06-16","s":"Rejeté","t":"Droit à l'aide à mourir","div":"ART. 6","nc":0},{"num":"614","d":"2026-06-16","s":"En cours","t":"Droit à l'aide à mourir","div":"ART. 8","nc":0},{"num":"615","d":"2026-06-16","s":"Non soutenu","t":"Droit à l'aide à mourir","div":"ART. 10","nc":0},{"num":"625","d":"2026-06-16","s":"Rejeté","t":"Droit à l'aide à mourir","div":"ART. 2","nc":0},{"num":"622","d":"2026-06-16","s":"Rejeté","t":"Droit à l'aide à mourir","div":"ART. PREMIER","nc":0},{"num":"623","d":"2026-06-16","s":"Rejeté","t":"Droit à l'aide à mourir","div":"ART. 2","nc":0},{"num":"608","d":"2026-06-16","s":"Rejeté","t":"Droit à l'aide à mourir","div":"ART. 3","nc":0},{"num":"627","d":"2026-06-16","s":"Rejeté","t":"Droit à l'aide à mourir","div":"ART. 2","nc":0},{"num":"609","d":"2026-06-16","s":"Rejeté","t":"Droit à l'aide à mourir","div":"ART. 4","nc":0},{"num":"626","d":"2026-06-16","s":"Rejeté","t":"Droit à l'aide à mourir","div":"ART. 2","nc":0},{"num":"620","d":"2026-06-16","s":"En cours","t":"Droit à l'aide à mourir","div":"ART. 19 BIS","nc":0},{"num":"612","d":"2026-06-16","s":"En cours","t":"Droit à l'aide à mourir","div":"ART. 7","nc":0},{"num":"610","d":"2026-06-16","s":"Non soutenu","t":"Droit à l'aide à mourir","div":"ART. 5","nc":0},{"num":"607","d":"2026-06-16","s":"Rejeté","t":"Droit à l'aide à mourir","div":"ART. 2","nc":0},{"num":"619","d":"2026-06-16","s":"En cours","t":"Droit à l'aide à mourir","div":"ART. 16","nc":0},{"num":"616","d":"2026-06-16","s":"Non soutenu","t":"Droit à l'aide à mourir","div":"ART. 11","nc":0},{"num":"621","d":"2026-06-16","s":"Non soutenu","t":"Droit à l'aide à mourir","div":"TITRE","nc":0},{"num":"20","d":"2026-06-08","s":"Rejeté","t":"Réformer les bourses sur critères sociaux et lutter contre la précarité étudiante","div":"ART. PREMIER","nc":10},{"num":"21","d":"2026-06-08","s":"Rejeté","t":"Réformer les bourses sur critères sociaux et lutter contre la précarité étudiante","div":"ART. PREMIER","nc":10},{"num":"23","d":"2026-06-08","s":"Rejeté","t":"Réformer les bourses sur critères sociaux et lutter contre la précarité étudiante","div":"APRÈS ART. PREMIER","nc":10},{"num":"13","d":"2026-06-08","s":"En cours","t":"Réformer les bourses sur critères sociaux et lutter contre la précarité étudiante","div":"APRÈS ART. PREMIER","nc":0},{"num":"11","d":"2026-06-08","s":"Rejeté","t":"Réformer les bourses sur critères sociaux et lutter contre la précarité étudiante","div":"ART. PREMIER","nc":0},{"num":"10","d":"2026-06-08","s":"Rejeté","t":"Réformer les bourses sur critères sociaux et lutter contre la précarité étudiante","div":"ART. PREMIER","nc":0},{"num":"12","d":"2026-06-08","s":"Rejeté","t":"Réformer les bourses sur critères sociaux et lutter contre la précarité étudiante","div":"ART. 2","nc":0},{"num":"19","d":"2026-06-08","s":"Rejeté","t":"Réformer les bourses sur critères sociaux et lutter contre la précarité étudiante","div":"ART. PREMIER","nc":9},{"num":"22","d":"2026-06-08","s":"En cours","t":"Réformer les bourses sur critères sociaux et lutter contre la précarité étudiante","div":"APRÈS ART. PREMIER","nc":10},{"num":"14 (Rect)","d":"2026-06-08","s":"Adopté","t":"Réformer les bourses sur critères sociaux et lutter contre la précarité étudiante","div":"APRÈS ART. PREMIER","nc":0},{"num":"31","d":"2026-06-08","s":"Rejeté","t":"Nationalisation d'ArcelorMittal France","div":"ART. PREMIER","nc":0},{"num":"28","d":"2026-06-08","s":"Rejeté","t":"Nationalisation d'ArcelorMittal France","div":"APRÈS ART. 2","nc":0},{"num":"29","d":"2026-06-08","s":"Rejeté","t":"Nationalisation d'ArcelorMittal France","div":"ART. PREMIER","nc":0},{"num":"32","d":"2026-06-08","s":"Rejeté","t":"Nationalisation d'ArcelorMittal France","div":"ART. PREMIER","nc":0},{"num":"33","d":"2026-06-08","s":"Rejeté","t":"Nationalisation d'ArcelorMittal France","div":"TITRE","nc":0},{"num":"30","d":"2026-06-08","s":"Rejeté","t":"Nationalisation d'ArcelorMittal France","div":"ART. PREMIER","nc":0},{"num":"27","d":"2026-06-08","s":"Rejeté","t":"Nationalisation d'ArcelorMittal France","div":"ART. PREMIER","nc":0},{"num":"26","d":"2026-06-08","s":"Rejeté","t":"Nationalisation d'ArcelorMittal France","div":"ART. PREMIER","nc":0},{"num":"1106","d":"2026-05-15","s":"Non soutenu","t":"Protection et souveraineté agricoles","div":"ART. 8 TER","nc":0},{"num":"1101","d":"2026-05-15","s":"Non soutenu","t":"Protection et souveraineté agricoles","div":"ART. 5 TER","nc":0},{"num":"1089","d":"2026-05-15","s":"Non soutenu","t":"Protection et souveraineté agricoles","div":"ART. 4 BIS","nc":0},{"num":"1104","d":"2026-05-15","s":"Non soutenu","t":"Protection et souveraineté agricoles","div":"ART. 6","nc":0},{"num":"1105","d":"2026-05-15","s":"Non soutenu","t":"Protection et souveraineté agricoles","div":"ART. 8","nc":0},{"num":"1114","d":"2026-05-15","s":"En cours","t":"Protection et souveraineté agricoles","div":"ART. 15","nc":0},{"num":"1349","d":"2026-05-15","s":"En cours","t":"Protection et souveraineté agricoles","div":"APRÈS ART. 14","nc":0},{"num":"1120","d":"2026-05-15","s":"En cours","t":"Protection et souveraineté agricoles","div":"APRÈS ART. 11","nc":0},{"num":"1093","d":"2026-05-15","s":"Non soutenu","t":"Protection et souveraineté agricoles","div":"ART. 5","nc":0},{"num":"1102","d":"2026-05-15","s":"Tombé","t":"Protection et souveraineté agricoles","div":"ART. 5 TER","nc":0},{"num":"1088","d":"2026-05-15","s":"En cours","t":"Protection et souveraineté agricoles","div":"APRÈS ART. 2","nc":0},{"num":"1110","d":"2026-05-15","s":"Non soutenu","t":"Protection et souveraineté agricoles","div":"ART. 10","nc":0},{"num":"1091","d":"2026-05-15","s":"En cours","t":"Protection et souveraineté agricoles","div":"APRÈS ART. 5","nc":0},{"num":"647","d":"2026-04-29","s":"Rejeté","t":"Actualisation de la programmation militaire pour les années 2024 à 2030 et diverses dispositions intéressant la défense","div":"ART. PREMIER","nc":0},{"num":"607","d":"2026-04-29","s":"Rejeté","t":"Actualisation de la programmation militaire pour les années 2024 à 2030 et diverses dispositions intéressant la défense","div":"ART. 23","nc":0},{"num":"711","d":"2026-04-29","s":"Rejeté","t":"Actualisation de la programmation militaire pour les années 2024 à 2030 et diverses dispositions intéressant la défense","div":"ART. PREMIER","nc":0},{"num":"712","d":"2026-04-29","s":"Rejeté","t":"Actualisation de la programmation militaire pour les années 2024 à 2030 et diverses dispositions intéressant la défense","div":"ART. PREMIER","nc":0},{"num":"619","d":"2026-04-29","s":"Rejeté","t":"Actualisation de la programmation militaire pour les années 2024 à 2030 et diverses dispositions intéressant la défense","div":"ART. PREMIER","nc":0},{"num":"633","d":"2026-04-29","s":"Tombé","t":"Actualisation de la programmation militaire pour les années 2024 à 2030 et diverses dispositions intéressant la défense","div":"ART. PREMIER","nc":0},{"num":"82","d":"2026-04-07","s":"Tombé","t":"Simplifier le millefeuille territorial par la collectivité unique","div":"APRÈS ART. 2","nc":1},{"num":"84","d":"2026-04-07","s":"Tombé","t":"Simplifier le millefeuille territorial par la collectivité unique","div":"APRÈS ART. 2","nc":3},{"num":"83","d":"2026-04-07","s":"Adopté","t":"Simplifier le millefeuille territorial par la collectivité unique","div":"ART. 2","nc":3},{"num":"20","d":"2026-04-02","s":"En cours","t":"Simplifier le millefeuille territorial par la collectivité unique","div":"ART. 2","nc":6},{"num":"22","d":"2026-04-02","s":"En cours","t":"Simplifier le millefeuille territorial par la collectivité unique","div":"ART. 2","nc":6},{"num":"66","d":"2026-03-23","s":"En cours","t":"Renforcer le contrôle, la gouvernance et la responsabilité financière des agences et opérateurs de l’État","div":"APRÈS ART. 3","nc":87},{"num":"324","d":"2026-02-19","s":"Non soutenu","t":"Projet de loi relatif à la lutte contre les fraudes sociales et fiscales","div":"ART. 9 SEPTIES","nc":0},{"num":"317","d":"2026-02-19","s":"En cours","t":"Projet de loi relatif à la lutte contre les fraudes sociales et fiscales","div":"APRÈS ART. 18","nc":0},{"num":"329","d":"2026-02-19","s":"Non soutenu","t":"Projet de loi relatif à la lutte contre les fraudes sociales et fiscales","div":"ART. 9 OCTIES","nc":0},{"num":"260","d":"2026-02-19","s":"Non soutenu","t":"Projet de loi relatif à la lutte contre les fraudes sociales et fiscales","div":"APRÈS ART. 3 BIS A","nc":0},{"num":"70","d":"2026-02-12","s":"Rejeté","t":"Soins palliatifs","div":"ART. PREMIER","nc":0},{"num":"69","d":"2026-02-12","s":"Rejeté","t":"Soins palliatifs","div":"ART. PREMIER","nc":0},{"num":"68","d":"2026-02-12","s":"Rejeté","t":"Soins palliatifs","div":"ART. PREMIER","nc":0},{"num":"1086","d":"2026-02-12","s":"Rejeté","t":"Droit à l'aide à mourir","div":"ART. 4","nc":0},{"num":"1058","d":"2026-02-12","s":"Rejeté","t":"Droit à l'aide à mourir","div":"ART. 15","nc":0},{"num":"1085","d":"2026-02-12","s":"Rejeté","t":"Droit à l'aide à mourir","div":"ART. 4","nc":0},{"num":"1066","d":"2026-02-12","s":"Rejeté","t":"Droit à l'aide à mourir","div":"ART. 18","nc":0},{"num":"1067","d":"2026-02-12","s":"Rejeté","t":"Droit à l'aide à mourir","div":"ART. 19","nc":0},{"num":"1062","d":"2026-02-12","s":"Rejeté","t":"Droit à l'aide à mourir","div":"ART. 10","nc":0},{"num":"1068","d":"2026-02-12","s":"En cours","t":"Droit à l'aide à mourir","div":"ART. 7","nc":0},{"num":"1063","d":"2026-02-12","s":"Rejeté","t":"Droit à l'aide à mourir","div":"ART. 12","nc":0},{"num":"1064","d":"2026-02-12","s":"Rejeté","t":"Droit à l'aide à mourir","div":"ART. 13","nc":0},{"num":"1055","d":"2026-02-12","s":"Rejeté","t":"Droit à l'aide à mourir","div":"ART. 14","nc":0},{"num":"1059","d":"2026-02-12","s":"En cours","t":"Droit à l'aide à mourir","div":"ART. 15","nc":0},{"num":"1091","d":"2026-02-12","s":"Rejeté","t":"Droit à l'aide à mourir","div":"TITRE","nc":0},{"num":"1078","d":"2026-02-12","s":"Rejeté","t":"Droit à l'aide à mourir","div":"ART. 17","nc":0},{"num":"1077","d":"2026-02-12","s":"Rejeté","t":"Droit à l'aide à mourir","div":"ART. 6","nc":0},{"num":"1080","d":"2026-02-12","s":"Rejeté","t":"Droit à l'aide à mourir","div":"ART. 5","nc":0},{"num":"1088","d":"2026-02-12","s":"En cours","t":"Droit à l'aide à mourir","div":"ART. 4","nc":0},{"num":"1072","d":"2026-02-12","s":"Rejeté","t":"Droit à l'aide à mourir","div":"ART. 5","nc":0},{"num":"1079","d":"2026-02-12","s":"Rejeté","t":"Droit à l'aide à mourir","div":"ART. 17","nc":0},{"num":"1065","d":"2026-02-12","s":"Rejeté","t":"Droit à l'aide à mourir","div":"ART. 17","nc":0},{"num":"1083","d":"2026-02-12","s":"Rejeté","t":"Droit à l'aide à mourir","div":"ART. 11","nc":0},{"num":"1071","d":"2026-02-12","s":"Rejeté","t":"Droit à l'aide à mourir","div":"ART. 4","nc":0},{"num":"1070","d":"2026-02-12","s":"Rejeté","t":"Droit à l'aide à mourir","div":"ART. 6","nc":0},{"num":"1056","d":"2026-02-12","s":"Non soutenu","t":"Droit à l'aide à mourir","div":"ART. 14","nc":0},{"num":"1075","d":"2026-02-12","s":"Rejeté","t":"Droit à l'aide à mourir","div":"ART. 9","nc":0},{"num":"1074","d":"2026-02-12","s":"Rejeté","t":"Droit à l'aide à mourir","div":"ART. 6","nc":0},{"num":"1082","d":"2026-02-12","s":"Rejeté","t":"Droit à l'aide à mourir","div":"ART. 16","nc":0},{"num":"1084","d":"2026-02-12","s":"Tombé","t":"Droit à l'aide à mourir","div":"ART. 2","nc":0},{"num":"1090","d":"2026-02-12","s":"Rejeté","t":"Droit à l'aide à mourir","div":"ART. 4","nc":0},{"num":"1069","d":"2026-02-12","s":"En cours","t":"Droit à l'aide à mourir","div":"ART. 7","nc":0},{"num":"1076","d":"2026-02-12","s":"En cours","t":"Droit à l'aide à mourir","div":"ART. 6","nc":0},{"num":"1087","d":"2026-02-12","s":"Rejeté","t":"Droit à l'aide à mourir","div":"ART. 4","nc":0},{"num":"1060","d":"2026-02-12","s":"En cours","t":"Droit à l'aide à mourir","div":"ART. 17","nc":0},{"num":"1081","d":"2026-02-12","s":"Rejeté","t":"Droit à l'aide à mourir","div":"ART. 5","nc":0},{"num":"1073","d":"2026-02-12","s":"En cours","t":"Droit à l'aide à mourir","div":"ART. 6","nc":0},{"num":"1061","d":"2026-02-12","s":"Rejeté","t":"Droit à l'aide à mourir","div":"ART. 17","nc":0},{"num":"1089","d":"2026-02-12","s":"Rejeté","t":"Droit à l'aide à mourir","div":"ART. 4","nc":0},{"num":"1047","d":"2026-02-11","s":"Rejeté","t":"Droit à l'aide à mourir","div":"ART. 8","nc":0},{"num":"844","d":"2026-02-11","s":"Rejeté","t":"Droit à l'aide à mourir","div":"ART. 2","nc":0},{"num":"1048","d":"2026-02-11","s":"Rejeté","t":"Droit à l'aide à mourir","div":"ART. 9","nc":0},{"num":"835","d":"2026-02-11","s":"Rejeté","t":"Droit à l'aide à mourir","div":"ART. 2","nc":0},{"num":"851","d":"2026-02-11","s":"Rejeté","t":"Droit à l'aide à mourir","div":"ART. 4","nc":0},{"num":"833","d":"2026-02-11","s":"Rejeté","t":"Droit à l'aide à mourir","div":"ART. 2","nc":0},{"num":"1053","d":"2026-02-11","s":"Rejeté","t":"Droit à l'aide à mourir","div":"ART. 10","nc":0},{"num":"1050","d":"2026-02-11","s":"Rejeté","t":"Droit à l'aide à mourir","div":"ART. 9","nc":0},{"num":"831","d":"2026-02-11","s":"Rejeté","t":"Droit à l'aide à mourir","div":"ART. 2","nc":0},{"num":"1017","d":"2026-02-11","s":"Rejeté","t":"Droit à l'aide à mourir","div":"ART. 5","nc":0},{"num":"1041","d":"2026-02-11","s":"Rejeté","t":"Droit à l'aide à mourir","div":"ART. 7","nc":0}],"nb_total_amendements":674,"questions":[{"ty":"QE","num":"16231","d":"2026-06-23","t":"Rendement de la CDHR pour 2025","r":"impôt sur le revenu","m":"Économie, finances, souveraineté industrielle, énergétique et numérique","s":"En attente de réponse"},{"ty":"QOSD","num":"768","d":"2026-06-09","t":"Réforme des bourses étudiantes","r":"enseignement supérieur","m":"Enseignement supérieur, recherche et espace","s":"En attente de réponse"},{"ty":"QE","num":"15585","d":"2026-06-02","t":"Recouvrement des indus de bourses pour assiduité","r":"enseignement supérieur","m":"Enseignement supérieur, recherche et espace","s":"En attente de réponse"},{"ty":"QE","num":"13230","d":"2026-03-03","t":"Fuite de données personnelles du fichier FICOBA","r":"administration","m":"Économie, finances, souveraineté industrielle, énergétique et numérique","s":"Réponse publiée"},{"ty":"QE","num":"13183","d":"2026-02-24","t":"Attribution de l'allocation d'éducation de l'enfant handicapé","r":"prestations familiales","m":"Santé, familles, autonomie et personnes handicapées","s":"En attente de réponse"},{"ty":"QOSD","num":"528","d":"2026-01-20","t":"Prolifération du frelon asiatique en Alsace","r":"animaux","m":"Transition écologique, biodiversité et négociations internationales","s":"Réponse publiée"},{"ty":"QE","num":"11909","d":"2025-12-23","t":"Gestion de la dermatose nodulaire contagieuse (DNC) des bovins","r":"élevage","m":"Agriculture, agro-alimentaire et souveraineté alimentaire","s":"En attente de réponse"},{"ty":"QE","num":"8521","d":"2025-07-15","t":"Monopole des entreprises locales de distribution (ELD)","r":"énergie et carburants","m":"Industrie et énergie","s":"En attente de réponse"},{"ty":"QE","num":"8502","d":"2025-07-15","t":"Recours aux cabinets de conseil par les collectivités locales","r":"collectivités territoriales","m":"Aménagement du territoire et décentralisation","s":"En attente de réponse"},{"ty":"QE","num":"8524","d":"2025-07-15","t":"Recentralisation de l'aide sociale à l'enfance au niveau de l'État","r":"enfants","m":"Travail, santé, solidarités et familles","s":"En attente de réponse"},{"ty":"QE","num":"7325","d":"2025-06-10","t":"Balance agroalimentaire et agricole 2024","r":"commerce extérieur","m":"Agriculture, souveraineté alimentaire","s":"Réponse publiée"},{"ty":"QOSD","num":"356","d":"2025-06-03","t":"Difficultés liées à l'enseignement de l'allemand","r":"enseignement","m":"Éducation nationale, enseignement supérieur et recherche","s":"Réponse publiée"},{"ty":"QE","num":"6728","d":"2025-05-20","t":"Infractions routières constatables sans interception","r":"crimes, délits et contraventions","m":"Intérieur","s":"En attente de réponse"},{"ty":"QE","num":"5812","d":"2025-04-08","t":"Groenland","r":"politique extérieure","m":"Europe et affaires étrangères","s":"Réponse publiée"},{"ty":"QE","num":"5517","d":"2025-04-01","t":"Budget Défense exécuté en 2024","r":"défense","m":"Armées","s":"Réponse publiée"},{"ty":"QE","num":"4832","d":"2025-03-11","t":"Réforme des certificats d'économie d'énergie","r":"énergie et carburants","m":"Industrie et énergie","s":"Réponse publiée"},{"ty":"QE","num":"3190","d":"2025-01-14","t":"Coût final des jeux Olympiques et Paralympiques de Paris 2024","r":"sports","m":"Sports, jeunesse et vie associative","s":"Réponse publiée"},{"ty":"QE","num":"3158","d":"2025-01-14","t":"Manque d'AESH dans les établissements scolaires","r":"personnes handicapées","m":"Éducation nationale, enseignement supérieur et recherche","s":"Réponse publiée"},{"ty":"QE","num":"3128","d":"2025-01-14","t":"Possibilité de transférer la somme d'un CPF","r":"formation professionnelle et apprentissage","m":"Travail, santé, solidarités et familles","s":"Réponse publiée"},{"ty":"QE","num":"3167","d":"2025-01-14","t":"Relations avec la Syrie","r":"politique extérieure","m":"Europe et affaires étrangères","s":"Réponse publiée"},{"ty":"QE","num":"2546","d":"2024-12-03","t":"Partage de la somme du compte personnel de formation (CPF)","r":"formation professionnelle et apprentissage","m":"Travail et emploi","s":"Retrait à l'initiative de l'auteur"},{"ty":"QE","num":"2225","d":"2024-11-26","t":"Fiscalité des mutuelles","r":"assurance complémentaire","m":"Économie, finances et industrie","s":"En attente de réponse"},{"ty":"QE","num":"1932","d":"2024-11-12","t":"Nombre de guichets automatiques bancaires","r":"moyens de paiement","m":"Économie, finances et industrie","s":"Réponse publiée"},{"ty":"QE","num":"1803","d":"2024-11-05","t":"Priorités européennes de la France","r":"Union européenne","m":"Europe","s":"Réponse publiée"},{"ty":"QE","num":"1762","d":"2024-11-05","t":"Objectif de 3 % de dépenses de recherche fixé par la stratégie de Lisbonne","r":"recherche et innovation","m":"Enseignement supérieur et recherche","s":"Réponse publiée"},{"ty":"QE","num":"703","d":"2024-10-08","t":"Franchises pour le remboursement des soins d'affections de longue durée","r":"sécurité sociale","m":"Santé et accès aux soins","s":"En attente de réponse"},{"ty":"QE","num":"380","d":"2024-10-08","t":"Contrats d'apprentissage","r":"formation professionnelle et apprentissage","m":"Réussite scolaire et enseignement professionnel","s":"Réponse publiée"},{"ty":"QE","num":"23","d":"2024-10-01","t":"Fièvre catarrhale ovine","r":"élevage","m":"Agriculture, souveraineté alimentaire et forêt","s":"Réponse publiée"},{"ty":"QG","num":"865","d":null,"t":"Maîtrise de la dépense publique","r":"finances publiques","m":"Comptes publics","s":"Réponse publiée"}],"nb_total_questions":29,"rapports":[{"d":"2026-07-02","t":"rapport d'information déposé en application de l'article 146 du règlement, par la commission des finances, de l'économie générale et du contrôle budgétaire sur la mise en œuvre des repas CROUS à 1 eu…","ty":"Rapport d'information","q":"rapporteur"},{"d":"2026-03-23","t":"visant à instaurer une procédure simplifiée de recouvrement des créances commerciales incontestées","ty":"Rapport","q":"rapporteur"},{"d":"2026-03-23","t":"visant à instaurer une procédure simplifiée de recouvrement des créances commerciales incontestées","ty":"Proposition de loi","q":"rapporteur"},{"d":"2025-06-11","t":"rapport d'information déposé en application de l'article 146 du règlement, par la commission des finances, de l'économie générale et du contrôle budgétaire sur la réforme des bourses étudiantes","ty":"Rapport d'information","q":"rapporteur"},{"d":"2025-05-28","t":"Élever Alfred Dreyfus au grade du général de brigade","ty":"Proposition de loi","q":"rapporteur"},{"d":"2025-05-28","t":"Élever Alfred Dreyfus au grade du général de brigade","ty":"Rapport","q":"rapporteur"},{"d":"2025-01-21","t":"rapport d'information Ddadue","ty":"Rapport d'information","q":"rapporteur"}],"collaborateurs":[{"civ":"Mme","prenom":"Nadège","nom":"Heiligenstein"},{"civ":"M.","prenom":"Louis","nom":"Reboul"}],"liens":{"hatvp":"https://www.hatvp.fr/pages_nominatives/sitzenstuhl-charles","page_an":"https://www.assemblee-nationale.fr/dyn/deputes/PA794802","photo":"public/photos/794802.jpg","photo_an":"https://www.assemblee-nationale.fr/dyn/static/tribun/17/photos/carre/794802.jpg"}}