{"id":"DLR5L17N53765","titre":"Renforcement des outils de contrôle des cessions en nue-propriété","titre_court":"Renforcement des outils de contrôle des cessions en nue-propriété","url":"https://www.assemblee-nationale.fr/dyn/17/dossiers/renforcement_outil_controle_cessions_nue_propriete_17e","url_senat":null,"procedure":"Proposition de loi ordinaire","procedure_acceleree":false,"commission":"Lois","rapporteur":null,"statut":"en_commission","loi":null,"date_derniere_etape":"2026-02-17","etapes":[{"date":"2026-02-17","chambre":"AN","type":"depot","libelle":"1er dépôt d'une initiative.","url_document":null},{"date":"2026-02-17","chambre":"AN","type":"commission","libelle":"Renvoi en commission au fond","url_document":null}],"scrutins":[],"amendements":null}