{"id":"DLR5L17N53172","titre":"Pour la protection des transporteurs routiers et la souveraineté logistique française","titre_court":"Pour la protection des transporteurs routiers et la souveraineté logistique française","url":"https://www.assemblee-nationale.fr/dyn/17/dossiers/pour_protection_transporteurs_routiers_souverainete_logistique_francaise_17e","url_senat":null,"procedure":"Proposition de loi ordinaire","procedure_acceleree":false,"commission":"Développement durable","rapporteur":null,"statut":"en_commission","loi":null,"date_derniere_etape":"2025-11-18","etapes":[{"date":"2025-11-18","chambre":"AN","type":"depot","libelle":"1er dépôt d'une initiative.","url_document":null},{"date":"2025-11-18","chambre":"AN","type":"commission","libelle":"Renvoi en commission au fond","url_document":null}],"scrutins":[],"amendements":null,"documents":[{"uid":"PIONANR5L17B2092","type":"PION","type_libelle":"Proposition de loi","titre":"proposition de loi pour la protection des transporteurs routiers et la souveraineté logistique française","date":"2025-11-18"}]}