{"id":"DLR5L17N52999","titre":"Proposition de loi relative à la lutte contre l'obésité par la réduction des sucres ajoutés dans l'alimentation","titre_court":null,"url":"https://www.assemblee-nationale.fr/dyn/17/dossiers/DLR5L17N52999","url_senat":"http://www.senat.fr/dossier-legislatif/ppl25-019.html","procedure":"Proposition de loi ordinaire","procedure_acceleree":false,"commission":"Affaires sociales","rapporteur":null,"statut":"en_commission","loi":null,"date_derniere_etape":"2025-10-14","etapes":[{"date":"2025-10-14","chambre":"Sénat","type":"depot","libelle":"1er dépôt d'une initiative.","url_document":null},{"date":"2025-10-14","chambre":"Sénat","type":"commission","libelle":"Renvoi en commission au fond","url_document":null}],"scrutins":[],"amendements":null}