{"id":"DLR5L17N53418","titre":"Protéger l’alimentation des Français et des Françaises des contaminations au cadmium","titre_court":"Protéger l’alimentation des Français et des Françaises des contaminations au cadmium","url":"https://www.assemblee-nationale.fr/dyn/17/dossiers/_proteger_alimentation_francais_et_francaises_des_contaminations_au_cadmium_17e","url_senat":null,"procedure":"Proposition de loi ordinaire","procedure_acceleree":false,"commission":"Affaires économiques","rapporteur":"Benoît Biteau","statut":"en_commission","loi":null,"date_derniere_etape":"2026-02-11","etapes":[{"date":"2025-12-23","chambre":"AN","type":"depot","libelle":"1er dépôt d'une initiative.","url_document":null},{"date":"2025-12-23","chambre":"AN","type":"commission","libelle":"Renvoi en commission au fond","url_document":null},{"date":"2026-01-20","chambre":"AN","type":"commission","libelle":"Nomination de rapporteur","url_document":null},{"date":"2026-01-20","chambre":"AN","type":"commission","libelle":"Réunion de commission","url_document":null},{"date":"2026-02-04","chambre":"AN","type":"commission","libelle":"Réunion de commission","url_document":null},{"date":"2026-02-04","chambre":"AN","type":"commission","libelle":"Dépôt de rapport","url_document":null},{"date":"2026-02-11","chambre":"AN","type":"commission","libelle":"Réunion de commission","url_document":null}],"scrutins":[],"amendements":{"total":92,"par_sort":{"En cours":85,"Rejeté":6,"Adopté":1}}}