{"id":"DLR5L17N52946","titre":"Renforcer les droits des bailleurs commerciaux lors des procédures collectives","titre_court":"Renforcer les droits des bailleurs commerciaux lors des procédures collectives","url":"https://www.assemblee-nationale.fr/dyn/17/dossiers/renforcer_droits_bailleurs_commerciaux_procedures_collectives_17e","url_senat":null,"procedure":"Proposition de loi ordinaire","procedure_acceleree":false,"commission":"Affaires économiques","rapporteur":null,"statut":"en_commission","loi":null,"date_derniere_etape":"2025-10-14","etapes":[{"date":"2025-10-14","chambre":"AN","type":"depot","libelle":"1er dépôt d'une initiative.","url_document":null},{"date":"2025-10-14","chambre":"AN","type":"commission","libelle":"Renvoi en commission au fond","url_document":null}],"scrutins":[],"amendements":null}