{"id":"DLR5L17N54653","titre":"Instaurer la suspension du paiement du loyer pour les logements ne protégeant pas leurs occupants des fortes chaleurs","titre_court":"Instaurer la suspension du paiement du loyer pour les logements ne protégeant pas leurs occupants des fortes chaleurs","url":"https://www.assemblee-nationale.fr/dyn/17/dossiers/suspension_loyer_protection_chaleurs_17e","url_senat":null,"procedure":"Proposition de loi ordinaire","procedure_acceleree":false,"commission":"Affaires économiques","rapporteur":null,"statut":"en_commission","loi":null,"date_derniere_etape":"2026-07-07","etapes":[{"date":"2026-07-07","chambre":"AN","type":"depot","libelle":"1er dépôt d'une initiative.","url_document":null},{"date":"2026-07-07","chambre":"AN","type":"commission","libelle":"Renvoi en commission au fond","url_document":null}],"scrutins":[],"amendements":null}