{"id":"DLR5L17N51597","titre":"Proposition de loi visant à reconnaître le rôle des acteurs assurant des soins de troisième recours en psychiatrie","titre_court":"visant à intégrer les centres experts en santé mentale dans le code de la santé publique","url":"https://www.assemblee-nationale.fr/dyn/17/dossiers/DLR5L17N51597","url_senat":"http://www.senat.fr/dossier-legislatif/ppl24-385.html","procedure":"Proposition de loi ordinaire","procedure_acceleree":false,"commission":"Affaires sociales","rapporteur":null,"statut":"en_commission","loi":null,"date_derniere_etape":"2025-12-16","etapes":[{"date":"2025-02-27","chambre":"Sénat","type":"depot","libelle":"1er dépôt d'une initiative.","url_document":null},{"date":"2025-02-27","chambre":"Sénat","type":"commission","libelle":"Renvoi en commission au fond","url_document":null},{"date":"2025-12-10","chambre":"Sénat","type":"commission","libelle":"Dépôt de rapport","url_document":null},{"date":"2025-12-16","chambre":"Sénat","type":"adoption","libelle":"Décision — adoptée","url_document":null},{"date":"2025-12-16","chambre":"AN","type":"depot","libelle":"Dépôt d'une initiative en navette","url_document":null},{"date":"2025-12-16","chambre":"AN","type":"commission","libelle":"Renvoi en commission au fond","url_document":null}],"scrutins":[],"amendements":null,"documents":[{"uid":"PIONANR5L17B2249","type":"PION","type_libelle":"Proposition de loi","titre":"proposition de loi visant à reconnaître le rôle des acteurs assurant des soins de troisième recours en psychiatrie","date":"2025-12-16"}]}